CHANGELOG
LICENSE
MANIFEST.in
README.md
requirements.txt
setup.cfg
setup.py
docs/index.html
docs/keywords.html
src/SeleniumProxy/__init__.py
src/SeleniumProxy/_version.py
src/SeleniumProxy/logger.py
src/SeleniumProxy/keywords/__init__.py
src/SeleniumProxy/keywords/browser_keywords.py
src/SeleniumProxy/keywords/http_keywords.py
src/SeleniumProxy/proxy/__init__.py
src/SeleniumProxy/proxy/cert.py
src/SeleniumProxy/proxy/client.py
src/SeleniumProxy/proxy/handler.py
src/SeleniumProxy/proxy/modifier.py
src/SeleniumProxy/proxy/proxy2.py
src/SeleniumProxy/proxy/server.py
src/SeleniumProxy/proxy/storage.py
src/SeleniumProxy/proxy/util.py
src/SeleniumProxy/webdriver/__init__.py
src/SeleniumProxy/webdriver/browser.py
src/SeleniumProxy/webdriver/request.py
src/robotframework_seleniumproxy.egg-info/PKG-INFO
src/robotframework_seleniumproxy.egg-info/SOURCES.txt
src/robotframework_seleniumproxy.egg-info/dependency_links.txt
src/robotframework_seleniumproxy.egg-info/requires.txt
src/robotframework_seleniumproxy.egg-info/top_level.txt