Metadata-Version: 2.1
Name: robotframework-seleniumproxy
Version: 0.0.4
Summary: Capture requests/responses generated with Seleniums Webdriver
Home-page: https://github.com/teaglebuilt/robotframework-seleniumproxy
Author: Dillan Teagle
Author-email: dillan@teaglebuilt.com
License: MIT
Keywords: selenium webdriver proxy robotframework seleniumlibrary network activity request response
Platform: UNKNOWN
Classifier: Development Status :: 4 - Beta
Classifier: Intended Audience :: Developers
Classifier: Topic :: Software Development :: Testing
Classifier: License :: OSI Approved :: MIT License
Classifier: Programming Language :: Python :: 3.6
Classifier: Programming Language :: Python :: 3.7
Classifier: Programming Language :: Python :: 3.8
